Workbook

Sheet INICIO
A1: CONTROL DE INVENTARIO Y REVENTA — EDICIÓN GRATUITA
A2: Registra hasta 50 SKU, ventas, comisiones, envíos y resultados calculados con tus propios datos
B5: INICIO RÁPIDO
B6: 1. | C6: Configura la fecha de control, los canales, las comisiones introducidas y el aviso de antigüedad en CONFIG.
B7: 2. | C7: Sustituye las tres filas de ejemplo por tus propios artículos. Esta edición incluye 50 filas de SKU.
B8: 3. | C8: Actualiza el estado y los campos de venta cuando se complete una operación.
B9: 4. | C9: Revisa el resultado calculado por canal y la antigüedad en RESUMEN.
B12: LEYENDA DE COLOR
B13: Celdas amarillas | C13: Datos editables de stock y venta.
B14: Celdas azul gris | C14: Cálculos automáticos de costes, comisiones y resultado.
B15: Encabezados terracota | C15: Etiquetas de tablas y secciones.
B17: MAPA DEL ARCHIVO
B18: CONFIG | C18: Fecha de control, categorías, canales y supuestos de comisión.
B19: INVENTARIO | C19: Una fila por SKU; el coste de preparación y el precio de venta son totales de la línea, no importes por unidad.
B20: CANALES | C20: Importes de venta, comisiones y resultado calculado por canal.
B21: RESUMEN | C21: Coste del stock, rotación, resultado calculado y antigüedad.
B22: CONTROLES | C22: Cuadres de coste, ventas y resultado calculado.
B25: EDICIÓN GRATUITA
B26: Incluye 50 SKU. La versión completa amplía la capacidad a 200 SKU y conserva el mismo flujo de registro.
B27: IMPORTANTE
B28: Herramienta general de registro y planificación basada en datos introducidos por el usuario. Las comisiones son supuestos editables. No constituye asesoramiento fiscal, jurídico, contable, financiero, comercial ni profesional; no determina obligaciones, deducibilidad, cumplimiento, resultado o decisiones de venta. Verifica por separado las reglas y tarifas vigentes de cada plataforma.
B34: Ver la versión completa para 200 SKU

Sheet CONFIG
A1: CONFIG
A2: Usa nombres de canal genéricos o sustitúyelos por las plataformas que quieras registrar.
B5: GENERAL
B6: Fecha de control | C6: 46252
B7: Moneda | C7: EUR (€)
B8: Aviso de antigüedad (días) | C8: 90
B11: CATEGORÍAS | E11: SUPUESTOS DE COMISIÓN POR CANAL
B12: Ropa | E12: Marketplace A | F12: 0.12
B13: Calzado | E13: Marketplace B | F13: 0.1
B14: Accesorios | E14: Tienda social | F14: 0.08
B15: Hogar | E15: Venta directa | F15: 0
B16: Electrónica
B17: Coleccionismo
B18: Libros y multimedia | E18: Estado | F18: Activo
B19: Otros | E19: Estado | F19: Vendido
E20: Estado | F20: Devuelto
E21: Estado | F21: Donado

Sheet INVENTARIO
A1: INVENTARIO Y VENTAS — 50 SKU
A2: Una fila por SKU. Las celdas amarillas son editables; los cálculos usan exclusivamente los datos introducidos.
A7: SKU | B7: Fecha de compra | C7: Artículo | D7: Categoría | E7: Cantidad | F7: Coste unitario | G7: Preparación (total línea) | H7: Coste total | I7: Precio publicado | J7: Canal | K7: Estado | L7: Fecha de venta | M7: Precio de venta total | N7: Comisión % | O7: Comisión plataforma | P7: Envío cobrado | Q7: Envío pagado | R7: Entrada neta calculada | S7: Resultado calculado | T7: Margen calculado | U7: Días en inventario
A8: RS-001 | B8: 46144 | C8: Chaqueta de lana vintage | D8: Ropa | E8: 1 | F8: 28 | G8: 6 | H8: =IF($A8="","",$E8*$F8+$G8) | I8: 95 | J8: Marketplace A | K8: Vendido | L8: 46187 | M8: 88 | N8: =IF($J8="","",IFERROR(INDEX(CONFIG!$F$12:$F$15,MATCH($J8,CONFIG!$E$12:$E$15,0)),0)) | O8: =IF($K8<>"Vendido",0,IF($M8="",0,$M8*$N8)) | P8: 8 | Q8: 12 | R8: =IF($K8<>"Vendido",0,$M8-$O8+$P8-$Q8) | S8: =IF($A8="","",IF($K8<>"Vendido",0,$R8-$H8)) | T8: =IFERROR($S8/$R8,0) | U8: =IF($B8="","",MAX(0,IF($L8<>"",$L8-$B8,CONFIG!$C$6-$B8)))
A9: RS-002 | B9: 46181 | C9: Botines de cuero | D9: Calzado | E9: 1 | F9: 35 | G9: 8 | H9: =IF($A9="","",$E9*$F9+$G9) | I9: 110 | J9: Marketplace B | K9: Activo | M9: 0 | N9: =IF($J9="","",IFERROR(INDEX(CONFIG!$F$12:$F$15,MATCH($J9,CONFIG!$E$12:$E$15,0)),0)) | O9: =IF($K9<>"Vendido",0,IF($M9="",0,$M9*$N9)) | P9: 0 | Q9: 0 | R9: =IF($K9<>"Vendido",0,$M9-$O9+$P9-$Q9) | S9: =IF($A9="","",IF($K9<>"Vendido",0,$R9-$H9)) | T9: =IFERROR($S9/$R9,0) | U9: =IF($B9="","",MAX(0,IF($L9<>"",$L9-$B9,CONFIG!$C$6-$B9)))
A10: RS-003 | B10: 46204 | C10: Lámpara de mesa de cerámica | D10: Hogar | E10: 1 | F10: 18 | G10: 4 | H10: =IF($A10="","",$E10*$F10+$G10) | I10: 72 | J10: Venta directa | K10: Vendido | L10: 46225 | M10: 70 | N10: =IF($J10="","",IFERROR(INDEX(CONFIG!$F$12:$F$15,MATCH($J10,CONFIG!$E$12:$E$15,0)),0)) | O10: =IF($K10<>"Vendido",0,IF($M10="",0,$M10*$N10)) | P10: 0 | Q10: 10 | R10: =IF($K10<>"Vendido",0,$M10-$O10+$P10-$Q10) | S10: =IF($A10="","",IF($K10<>"Vendido",0,$R10-$H10)) | T10: =IFERROR($S10/$R10,0) | U10: =IF($B10="","",MAX(0,IF($L10<>"",$L10-$B10,CONFIG!$C$6-$B10)))
H11: =IF($A11="","",$E11*$F11+$G11) | N11: =IF($J11="","",IFERROR(INDEX(CONFIG!$F$12:$F$15,MATCH($J11,CONFIG!$E$12:$E$15,0)),0)) | O11: =IF($K11<>"Vendido",0,IF($M11="",0,$M11*$N11)) | R11: =IF($K11<>"Vendido",0,$M11-$O11+$P11-$Q11) | S11: =IF($A11="","",IF($K11<>"Vendido",0,$R11-$H11)) | T11: =IFERROR($S11/$R11,0) | U11: =IF($B11="","",MAX(0,IF($L11<>"",$L11-$B11,CONFIG!$C$6-$B11)))
H12: =IF($A12="","",$E12*$F12+$G12) | N12: =IF($J12="","",IFERROR(INDEX(CONFIG!$F$12:$F$15,MATCH($J12,CONFIG!$E$12:$E$15,0)),0)) | O12: =IF($K12<>"Vendido",0,IF($M12="",0,$M12*$N12)) | R12: =IF($K12<>"Vendido",0,$M12-$O12+$P12-$Q12) | S12: =IF($A12="","",IF($K12<>"Vendido",0,$R12-$H12)) | T12: =IFERROR($S12/$R12,0) | U12: =IF($B12="","",MAX(0,IF($L12<>"",$L12-$B12,CONFIG!$C$6-$B12)))
H13: =IF($A13="","",$E13*$F13+$G13) | N13: =IF($J13="","",IFERROR(INDEX(CONFIG!$F$12:$F$15,MATCH($J13,CONFIG!$E$12:$E$15,0)),0)) | O13: =IF($K13<>"Vendido",0,IF($M13="",0,$M13*$N13)) | R13: =IF($K13<>"Vendido",0,$M13-$O13+$P13-$Q13) | S13: =IF($A13="","",IF($K13<>"Vendido",0,$R13-$H13)) | T13: =IFERROR($S13/$R13,0) | U13: =IF($B13="","",MAX(0,IF($L13<>"",$L13-$B13,CONFIG!$C$6-$B13)))
H14: =IF($A14="","",$E14*$F14+$G14) | N14: =IF($J14="","",IFERROR(INDEX(CONFIG!$F$12:$F$15,MATCH($J14,CONFIG!$E$12:$E$15,0)),0)) | O14: =IF($K14<>"Vendido",0,IF($M14="",0,$M14*$N14)) | R14: =IF($K14<>"Vendido",0,$M14-$O14+$P14-$Q14) | S14: =IF($A14="","",IF($K14<>"Vendido",0,$R14-$H14)) | T14: =IFERROR($S14/$R14,0) | U14: =IF($B14="","",MAX(0,IF($L14<>"",$L14-$B14,CONFIG!$C$6-$B14)))
H15: =IF($A15="","",$E15*$F15+$G15) | N15: =IF($J15="","",IFERROR(INDEX(CONFIG!$F$12:$F$15,MATCH($J15,CONFIG!$E$12:$E$15,0)),0)) | O15: =IF($K15<>"Vendido",0,IF($M15="",0,$M15*$N15)) | R15: =IF($K15<>"Vendido",0,$M15-$O15+$P15-$Q15) | S15: =IF($A15="","",IF($K15<>"Vendido",0,$R15-$H15)) | T15: =IFERROR($S15/$R15,0) | U15: =IF($B15="","",MAX(0,IF($L15<>"",$L15-$B15,CONFIG!$C$6-$B15)))
H16: =IF($A16="","",$E16*$F16+$G16) | N16: =IF($J16="","",IFERROR(INDEX(CONFIG!$F$12:$F$15,MATCH($J16,CONFIG!$E$12:$E$15,0)),0)) | O16: =IF($K16<>"Vendido",0,IF($M16="",0,$M16*$N16)) | R16: =IF($K16<>"Vendido",0,$M16-$O16+$P16-$Q16) | S16: =IF($A16="","",IF($K16<>"Vendido",0,$R16-$H16)) | T16: =IFERROR($S16/$R16,0) | U16: =IF($B16="","",MAX(0,IF($L16<>"",$L16-$B16,CONFIG!$C$6-$B16)))
H17: =IF($A17="","",$E17*$F17+$G17) | N17: =IF($J17="","",IFERROR(INDEX(CONFIG!$F$12:$F$15,MATCH($J17,CONFIG!$E$12:$E$15,0)),0)) | O17: =IF($K17<>"Vendido",0,IF($M17="",0,$M17*$N17)) | R17: =IF($K17<>"Vendido",0,$M17-$O17+$P17-$Q17) | S17: =IF($A17="","",IF($K17<>"Vendido",0,$R17-$H17)) | T17: =IFERROR($S17/$R17,0) | U17: =IF($B17="","",MAX(0,IF($L17<>"",$L17-$B17,CONFIG!$C$6-$B17)))
H18: =IF($A18="","",$E18*$F18+$G18) | N18: =IF($J18="","",IFERROR(INDEX(CONFIG!$F$12:$F$15,MATCH($J18,CONFIG!$E$12:$E$15,0)),0)) | O18: =IF($K18<>"Vendido",0,IF($M18="",0,$M18*$N18)) | R18: =IF($K18<>"Vendido",0,$M18-$O18+$P18-$Q18) | S18: =IF($A18="","",IF($K18<>"Vendido",0,$R18-$H18)) | T18: =IFERROR($S18/$R18,0) | U18: =IF($B18="","",MAX(0,IF($L18<>"",$L18-$B18,CONFIG!$C$6-$B18)))
H19: =IF($A19="","",$E19*$F19+$G19) | N19: =IF($J19="","",IFERROR(INDEX(CONFIG!$F$12:$F$15,MATCH($J19,CONFIG!$E$12:$E$15,0)),0)) | O19: =IF($K19<>"Vendido",0,IF($M19="",0,$M19*$N19)) | R19: =IF($K19<>"Vendido",0,$M19-$O19+$P19-$Q19) | S19: =IF($A19="","",IF($K19<>"Vendido",0,$R19-$H19)) | T19: =IFERROR($S19/$R19,0) | U19: =IF($B19="","",MAX(0,IF($L19<>"",$L19-$B19,CONFIG!$C$6-$B19)))
H20: =IF($A20="","",$E20*$F20+$G20) | N20: =IF($J20="","",IFERROR(INDEX(CONFIG!$F$12:$F$15,MATCH($J20,CONFIG!$E$12:$E$15,0)),0)) | O20: =IF($K20<>"Vendido",0,IF($M20="",0,$M20*$N20)) | R20: =IF($K20<>"Vendido",0,$M20-$O20+$P20-$Q20) | S20: =IF($A20="","",IF($K20<>"Vendido",0,$R20-$H20)) | T20: =IFERROR($S20/$R20,0) | U20: =IF($B20="","",MAX(0,IF($L20<>"",$L20-$B20,CONFIG!$C$6-$B20)))
H21: =IF($A21="","",$E21*$F21+$G21) | N21: =IF($J21="","",IFERROR(INDEX(CONFIG!$F$12:$F$15,MATCH($J21,CONFIG!$E$12:$E$15,0)),0)) | O21: =IF($K21<>"Vendido",0,IF($M21="",0,$M21*$N21)) | R21: =IF($K21<>"Vendido",0,$M21-$O21+$P21-$Q21) | S21: =IF($A21="","",IF($K21<>"Vendido",0,$R21-$H21)) | T21: =IFERROR($S21/$R21,0) | U21: =IF($B21="","",MAX(0,IF($L21<>"",$L21-$B21,CONFIG!$C$6-$B21)))
H22: =IF($A22="","",$E22*$F22+$G22) | N22: =IF($J22="","",IFERROR(INDEX(CONFIG!$F$12:$F$15,MATCH($J22,CONFIG!$E$12:$E$15,0)),0)) | O22: =IF($K22<>"Vendido",0,IF($M22="",0,$M22*$N22)) | R22: =IF($K22<>"Vendido",0,$M22-$O22+$P22-$Q22) | S22: =IF($A22="","",IF($K22<>"Vendido",0,$R22-$H22)) | T22: =IFERROR($S22/$R22,0) | U22: =IF($B22="","",MAX(0,IF($L22<>"",$L22-$B22,CONFIG!$C$6-$B22)))
... H57: =IF($A57="","",$E57*$F57+$G57) | N57: =IF($J57="","",IFERROR(INDEX(CONFIG!$F$12:$F$15,MATCH($J57,CONFIG!$E$12:$E$15,0)),0)) | O57: =IF($K57<>"Vendido",0,IF($M57="",0,$M57*$N57)) | R57: =IF($K57<>"Vendido",0,$M57-$O57+$P57-$Q57) | S57: =IF($A57="","",IF($K57<>"Vendido",0,$R57-$H57)) | T57: =IFERROR($S57/$R57,0) | U57: =IF($B57="","",MAX(0,IF($L57<>"",$L57-$B57,CONFIG!$C$6-$B57)))

Sheet CANALES
A1: CANALES
A2: Compara unidades vendidas e importes introducidos y calculados por canal.
B5: Canal | C5: Unidades vendidas | D5: Importe de ventas | E5: Comisiones de plataforma | F5: Entrada neta calculada | G5: Resultado calculado
B6: =CONFIG!E12 | C6: =SUMIFS(INVENTARIO!$E$8:$E$57,INVENTARIO!$J$8:$J$57,$B6,INVENTARIO!$K$8:$K$57,"Vendido") | D6: =SUMIFS(INVENTARIO!$M$8:$M$57,INVENTARIO!$J$8:$J$57,$B6,INVENTARIO!$K$8:$K$57,"Vendido") | E6: =SUMIFS(INVENTARIO!$O$8:$O$57,INVENTARIO!$J$8:$J$57,$B6) | F6: =SUMIFS(INVENTARIO!$R$8:$R$57,INVENTARIO!$J$8:$J$57,$B6) | G6: =SUMIFS(INVENTARIO!$S$8:$S$57,INVENTARIO!$J$8:$J$57,$B6)
B7: =CONFIG!E13 | C7: =SUMIFS(INVENTARIO!$E$8:$E$57,INVENTARIO!$J$8:$J$57,$B7,INVENTARIO!$K$8:$K$57,"Vendido") | D7: =SUMIFS(INVENTARIO!$M$8:$M$57,INVENTARIO!$J$8:$J$57,$B7,INVENTARIO!$K$8:$K$57,"Vendido") | E7: =SUMIFS(INVENTARIO!$O$8:$O$57,INVENTARIO!$J$8:$J$57,$B7) | F7: =SUMIFS(INVENTARIO!$R$8:$R$57,INVENTARIO!$J$8:$J$57,$B7) | G7: =SUMIFS(INVENTARIO!$S$8:$S$57,INVENTARIO!$J$8:$J$57,$B7)
B8: =CONFIG!E14 | C8: =SUMIFS(INVENTARIO!$E$8:$E$57,INVENTARIO!$J$8:$J$57,$B8,INVENTARIO!$K$8:$K$57,"Vendido") | D8: =SUMIFS(INVENTARIO!$M$8:$M$57,INVENTARIO!$J$8:$J$57,$B8,INVENTARIO!$K$8:$K$57,"Vendido") | E8: =SUMIFS(INVENTARIO!$O$8:$O$57,INVENTARIO!$J$8:$J$57,$B8) | F8: =SUMIFS(INVENTARIO!$R$8:$R$57,INVENTARIO!$J$8:$J$57,$B8) | G8: =SUMIFS(INVENTARIO!$S$8:$S$57,INVENTARIO!$J$8:$J$57,$B8)
B9: =CONFIG!E15 | C9: =SUMIFS(INVENTARIO!$E$8:$E$57,INVENTARIO!$J$8:$J$57,$B9,INVENTARIO!$K$8:$K$57,"Vendido") | D9: =SUMIFS(INVENTARIO!$M$8:$M$57,INVENTARIO!$J$8:$J$57,$B9,INVENTARIO!$K$8:$K$57,"Vendido") | E9: =SUMIFS(INVENTARIO!$O$8:$O$57,INVENTARIO!$J$8:$J$57,$B9) | F9: =SUMIFS(INVENTARIO!$R$8:$R$57,INVENTARIO!$J$8:$J$57,$B9) | G9: =SUMIFS(INVENTARIO!$S$8:$S$57,INVENTARIO!$J$8:$J$57,$B9)

Sheet RESUMEN
A1: RESUMEN DE REVENTA
A2: Coste registrado del stock, ventas, resultado calculado, rotación y antigüedad.
B5: COSTE DE STOCK ACTIVO | E5: IMPORTE DE VENTAS | H5: RESULTADO CALCULADO | J5: ROTACIÓN CALCULADA
B6: =SUMIFS(INVENTARIO!$H$8:$H$57,INVENTARIO!$K$8:$K$57,"Activo") | E6: =SUMIFS(INVENTARIO!$M$8:$M$57,INVENTARIO!$K$8:$K$57,"Vendido") | H6: =SUM(INVENTARIO!$S$8:$S$57) | J6: =IFERROR(SUMIFS(INVENTARIO!$E$8:$E$57,INVENTARIO!$K$8:$K$57,"Vendido")/SUM(INVENTARIO!$E$8:$E$57),0)
B10: Canal | C10: Resultado calculado | D10: Unidades vendidas
B11: =CONFIG!E12 | C11: =CANALES!G6 | D11: =CANALES!C6
B12: =CONFIG!E13 | C12: =CANALES!G7 | D12: =CANALES!C7
B13: =CONFIG!E14 | C13: =CANALES!G8 | D13: =CANALES!C8
B14: =CONFIG!E15 | C14: =CANALES!G9 | D14: =CANALES!C9
B17: Control de antigüedad | C17: Artículos
B18: Activos por encima del aviso | C18: =COUNTIFS(INVENTARIO!$K$8:$K$57,"Activo",INVENTARIO!$U$8:$U$57,">"&CONFIG!$C$8)
B19: Media de días hasta venta (SKU) | C19: =IFERROR(SUMIFS(INVENTARIO!$U$8:$U$57,INVENTARIO!$K$8:$K$57,"Vendido")/COUNTIFS(INVENTARIO!$K$8:$K$57,"Vendido"),0)

Sheet CONTROLES
A1: CONTROLES
A2: Cuadres internos de coste, ventas y resultado calculado.
A5: Control | B5: Calculado | C5: Referencia | D5: Estado | E5: Dónde revisar
A6: Coste total de ejemplo | B6: =INVENTARIO!$H$8 | C6: =INVENTARIO!$E$8*INVENTARIO!$F$8+INVENTARIO!$G$8 | D6: =IF(ABS(B6-C6)<0.01,"OK","REVISAR") | E6: INVENTARIO fila 8
A7: Resultado por canal | B7: =SUM(CANALES!$G$6:$G$9) | C7: =SUM(INVENTARIO!$S$8:$S$57) | D7: =IF(ABS(B7-C7)<0.01,"OK","REVISAR") | E7: CANALES frente a INVENTARIO
A8: Entrada neta calculada total | B8: =SUM(CANALES!$F$6:$F$9) | C8: =SUM(INVENTARIO!$R$8:$R$57) | D8: =IF(ABS(B8-C8)<0.01,"OK","REVISAR") | E8: Asignación por canal
A9: Filas vendidas incompletas | B9: =SUMPRODUCT((INVENTARIO!$K$8:$K$57="Vendido")*(((INVENTARIO!$L$8:$L$57="")+(INVENTARIO!$M$8:$M$57<=0))>0)) | C9: =0 | D9: =IF(ABS(B9-C9)<0.01,"OK","REVISAR") | E9: Cada artículo vendido se cuenta una vez si falta la fecha o el precio de venta total
A12: ESTADO DEL ARCHIVO | D12: =IF(COUNTIF(D6:D9,"REVISAR")=0,"OK","REVISAR")
